pyblish_photoshop/__init__.py
pyblish_photoshop/app.py
pyblish_photoshop/cli.py
pyblish_photoshop/version.py
pyblish_photoshop/plugins/__init__.py
pyblish_photoshop/plugins/collect_current_file.py
pyblish_photoshop-0.1.0.dist-info/LICENSE
pyblish_photoshop-0.1.0.dist-info/METADATA
pyblish_photoshop-0.1.0.dist-info/WHEEL
pyblish_photoshop-0.1.0.dist-info/entry_points.txt
pyblish_photoshop-0.1.0.dist-info/top_level.txt
pyblish_photoshop-0.1.0.dist-info/RECORD
