Metadata-Version: 2.1
Name: pyblish-photoshop
Version: 0.1.0
Summary: Pyblish integration for Adobe Photoshop
Home-page: https://github.com/pyblish/pyblish-photoshop
Author: Pyblish contributors
Author-email: me@mottosso.com
License: LGPL
Platform: UNKNOWN
Classifier: Development Status :: 4 - Beta
Classifier: Intended Audience :: Developers
Classifier: License :: OSI Approved :: GNU Lesser General Public License v3 (LGPLv3)
Classifier: Operating System :: Microsoft :: Windows
Classifier: Operating System :: Microsoft :: Windows :: Windows 10
Classifier: Programming Language :: Python :: 3 :: Only
Classifier: Programming Language :: Python :: 3.5
Classifier: Programming Language :: Python :: 3.6
Classifier: Programming Language :: Python :: 3.7
Classifier: Programming Language :: Python :: 3.8
Classifier: Topic :: Software Development :: Libraries :: Python Modules
Classifier: Topic :: Utilities
Requires-Dist: photoshop-python-api (>=0.12.0)
Requires-Dist: pyblish-base (>=1.2.1)
Requires-Dist: pyblish-lite (>=0.8.0)
Requires-Dist: click (>=7.0)
